<?xml version="1.0" encoding="ISO-8859-1"?>
<!-- XML generated by UTFXML Version 2.2 built 19-Aug-2010 -->
<UTFXML filename="echo_m11_player_en.utf">
<UTF_ROOT>
<test_voice name="0xBB947680" type="file" filename="echo_m11_player_en\dx_m11_0020_trent.wav"/>
<test_voice name="0xBB94AE86" type="file" filename="echo_m11_player_en\dx_m11_0040_trent.wav"/>
<test_voice name="0xBB803F88" type="file" filename="echo_m11_player_en\dx_m11_0100_trent.wav"/>
<test_voice name="0xBB80E78E" type="file" filename="echo_m11_player_en\dx_m11_0160_trent.wav"/>
<test_voice name="0x9BDCA887" type="file" filename="echo_m11_player_en\dx_m11_0250_trent.wav"/>
<test_voice name="0x9BDCE085" type="file" filename="echo_m11_player_en\dx_m11_0270_trent.wav"/>
<test_voice name="0x9BC83989" type="file" filename="echo_m11_player_en\dx_m11_0310_trent.wav"/>
<test_voice name="0x9BC8A98D" type="file" filename="echo_m11_player_en\dx_m11_0350_trent.wav"/>
<test_voice name="0xBBC91D80" type="file" filename="echo_m11_player_en\dx_m11_0380_trent.wav"/>
<test_voice name="0x8F81E98F" type="file" filename="echo_m11_player_en\dx_m11_1170_trent.wav"/>
<test_voice name="0x87F20009" type="file" filename="echo_m11_player_en\dx_m11_1180_edison.wav"/>
<test_voice name="0x87E60103" type="file" filename="echo_m11_player_en\dx_m11_1190_edison.wav"/>
<test_voice name="0xAFDD3682" type="file" filename="echo_m11_player_en\dx_m11_1200_trent.wav"/>
<test_voice name="0xBAC51703" type="file" filename="echo_m11_player_en\dx_m11_1210_edison.wav"/>
<test_voice name="0xBA991409" type="file" filename="echo_m11_player_en\dx_m11_1220_edison.wav"/>
<test_voice name="0x8FDD7A81" type="file" filename="echo_m11_player_en\dx_m11_1230_trent.wav"/>
<test_voice name="0xBA411209" type="file" filename="echo_m11_player_en\dx_m11_1240_edison.wav"/>
<test_voice name="0xBA551303" type="file" filename="echo_m11_player_en\dx_m11_1250_edison.wav"/>
<test_voice name="0xBA091009" type="file" filename="echo_m11_player_en\dx_m11_1260_edison.wav"/>
<test_voice name="0xBA1D1103" type="file" filename="echo_m11_player_en\dx_m11_1270_edison.wav"/>
<test_voice name="0xBBF11E09" type="file" filename="echo_m11_player_en\dx_m11_1280_edison.wav"/>
<test_voice name="0xBBE51F03" type="file" filename="echo_m11_player_en\dx_m11_1290_edison.wav"/>
<test_voice name="0xAFC93788" type="file" filename="echo_m11_player_en\dx_m11_1300_trent.wav"/>
<test_voice name="0xAE541903" type="file" filename="echo_m11_player_en\dx_m11_1350_edison.wav"/>
<test_voice name="0xAFC9EF8E" type="file" filename="echo_m11_player_en\dx_m11_1360_trent.wav"/>
<test_voice name="0xAE1C1B03" type="file" filename="echo_m11_player_en\dx_m11_1370_edison.wav"/>
<test_voice name="0xAFC81780" type="file" filename="echo_m11_player_en\dx_m11_1380_trent.wav"/>
<test_voice name="0xAFE41503" type="file" filename="echo_m11_player_en\dx_m11_1390_edison.wav"/>
<test_voice name="0x82D76A09" type="file" filename="echo_m11_player_en\dx_m11_1400_edison.wav"/>
<test_voice name="0xAF05A086" type="file" filename="echo_m11_player_en\dx_m11_1440_trent.wav"/>
<test_voice name="0x82536F03" type="file" filename="echo_m11_player_en\dx_m11_1450_edison.wav"/>
<test_voice name="0x820F6C09" type="file" filename="echo_m11_player_en\dx_m11_1460_edison.wav"/>
<test_voice name="0xAF113188" type="file" filename="echo_m11_player_en\dx_m11_1500_trent.wav"/>
<test_voice name="0x96C26103" type="file" filename="echo_m11_player_en\dx_m11_1510_edison.wav"/>
<test_voice name="0xB3962E83" type="file" filename="echo_m11_player_en\dx_m11_2010_trent.wav"/>
<test_voice name="0xB3966681" type="file" filename="echo_m11_player_en\dx_m11_2030_trent.wav"/>
<test_voice name="0xB396BE87" type="file" filename="echo_m11_player_en\dx_m11_2050_trent.wav"/>
<test_voice name="0xB396F685" type="file" filename="echo_m11_player_en\dx_m11_2070_trent.wav"/>
<test_voice name="0xB3970E8B" type="file" filename="echo_m11_player_en\dx_m11_2090_trent.wav"/>
<test_voice name="0xB3822F89" type="file" filename="echo_m11_player_en\dx_m11_2110_trent.wav"/>
<test_voice name="0xB382678B" type="file" filename="echo_m11_player_en\dx_m11_2130_trent.wav"/>
<test_voice name="0xB382BF8D" type="file" filename="echo_m11_player_en\dx_m11_2150_trent.wav"/>
<test_voice name="0xB382F78F" type="file" filename="echo_m11_player_en\dx_m11_2170_trent.wav"/>
<test_voice name="0xB3830F81" type="file" filename="echo_m11_player_en\dx_m11_2190_trent.wav"/>
<test_voice name="0x93DE6080" type="file" filename="echo_m11_player_en\dx_m11_2220_trent.wav"/>
<test_voice name="0x93DEB886" type="file" filename="echo_m11_player_en\dx_m11_2240_trent.wav"/>
</UTF_ROOT>
</UTFXML>
